latex_generator/__init__.py
latex_generator/latex_generator.py
latex_generator-no-mercy/__init__.py
latex_generator-no-mercy/latex_generator-no-mercy.py
latex_generator111/__init__.py
latex_generator111/latex_generator.py
latex_generator111/latex_generator111.py
latex_generator_no_mercy-0.1.0.dist-info/METADATA
latex_generator_no_mercy-0.1.0.dist-info/WHEEL
latex_generator_no_mercy-0.1.0.dist-info/top_level.txt
latex_generator_no_mercy-0.1.0.dist-info/RECORD
